setup.py
urilib/__init__.py
urilib/regex.py
urilib/tests.py
urilib/tools.py
urilib.egg-info/PKG-INFO
urilib.egg-info/SOURCES.txt
urilib.egg-info/dependency_links.txt
urilib.egg-info/top_level.txt