Metadata-Version: 1.0
Name: urilib
Version: 0.1
Summary: A library for managing URIs
Home-page: http://github.com/bsandrow/urilib
Author: Brandon Sandrowicz
Author-email: brandon@sandrowicz.org
License: UNKNOWN
Platform: UNKNOWN
